dash_gallery/DashGallery.py
dash_gallery/__init__.py
dash_gallery/_imports_.py
dash_gallery/dash_gallery.min.js
dash_gallery/dash_gallery.min.js.map
dash_gallery/metadata.json
dash_gallery/package-info.json
dash_gallery-0.0.1.dist-info/LICENSE
dash_gallery-0.0.1.dist-info/METADATA
dash_gallery-0.0.1.dist-info/WHEEL
dash_gallery-0.0.1.dist-info/top_level.txt
dash_gallery-0.0.1.dist-info/RECORD
