Metadata-Version: 2.1
Name: dash-gallery
Version: 0.0.1
Summary: React Image Gallery for Dash Plotly
Home-page: UNKNOWN
Author: innoWADEtech <innowadetech@gmail.com>
License: MIT
Platform: UNKNOWN
Classifier: Framework :: Dash
License-File: LICENSE
